{"skeleton":{"hash":"cRlBuQsRW/mzZA//ubpVYaXssLg","spine":"3.8.99","x":-178.12,"y":-57.36,"width":379.78,"height":436.36,"images":"./images/","audio":""},"bones":[{"name":"root"},{"name":"deng","parent":"root","x":-2.39,"y":325},{"name":"g11","parent":"deng","x":1.32,"y":-1.32},{"name":"g1","parent":"deng","y":-8.02},{"name":"g2","parent":"deng"}],"slots":[{"name":"deng","bone":"deng","attachment":"deng"},{"name":"ggg1_00000","bone":"g1","attachment":"ggg1_00000"},{"name":"ggg2_00000","bone":"g2","attachment":"ggg2_00000"},{"name":"g11","bone":"g11","attachment":"g11"}],"skins":[{"name":"default","attachments":{"deng":{"deng":{"y":0.5,"width":124,"height":107}},"g11":{"g11":{"width":114,"height":104}},"ggg1_00000":{"ggg1_00000":{"x":19.04,"y":-148.8,"width":370,"height":407}},"ggg2_00000":{"ggg2_00000":{"x":5.45,"y":-178.86,"scaleX":0.8669,"width":418,"height":407}}}}],"animations":{"animation":{"slots":{"ggg1_00000":{"color":[{"color":"ffffff97"},{"time":1.2667,"color":"fffffff1"},{"time":2.6333,"color":"ffffff97"}]},"ggg2_00000":{"color":[{"time":1.2667,"color":"ffffffff"}]}},"bones":{"g1":{"rotate":[{"angle":-7.09,"curve":0.25,"c3":0.75},{"time":1.2667,"angle":3.86,"curve":0.25,"c3":0.75},{"time":2.6667,"angle":-7.09}],"scale":[{"x":0.929,"y":1.118,"curve":"stepped"},{"time":2.6667,"x":0.929,"y":1.118}]},"g2":{"rotate":[{"angle":8.63,"curve":0.25,"c3":0.75},{"time":1.2667,"angle":-4.64,"curve":0.25,"c3":0.75},{"time":2.6667,"angle":8.63}],"scale":[{"x":0.976,"curve":"stepped"},{"time":2.6667,"x":0.976}]}}}}}