{"skeleton":{"hash":"0229kcVycquA984roZAplUoKo1A","spine":"3.8.99","x":-328.51,"y":-17.82,"width":641.92,"height":577.27,"images":"./images/","audio":"E:/Svn/塔防/美术_艾琳/角色/陆绩"},"bones":[{"name":"root"},{"name":"bone4","parent":"root","length":203.64,"rotation":122.73,"x":-194.65,"y":118.38,"color":"abe323ff"},{"name":"Zong","parent":"root","rotation":0.08,"color":"ff0000ff"},{"name":"Zong_Y","parent":"Zong","color":"ff0000ff"},{"name":"Body","parent":"Zong_Y","length":80.43,"rotation":91.22},{"name":"Body2","parent":"Body","length":80.43,"rotation":0.04,"x":80.93,"transform":"noScale"},{"name":"Body3","parent":"Body2","length":60.07,"rotation":-146.76,"x":106.29,"y":-94.53},{"name":"Body3b","parent":"Body3","length":60.07,"rotation":-8.25,"x":60.07},{"name":"Body5","parent":"Body2","length":67.99,"rotation":114.31,"x":83.74,"y":28.77,"color":"abe323ff"},{"name":"Body5b","parent":"Body5","length":67.99,"rotation":-8.79,"x":67.99,"color":"abe323ff"},{"name":"Body7","parent":"Body2","rotation":-1.14,"x":71.46,"y":19.41,"transform":"noScale"},{"name":"Body8","parent":"Body7","rotation":0.04,"x":101.3,"y":28.48,"color":"abe323ff"},{"name":"Body9","parent":"Body7","rotation":0.08,"x":127.84,"y":-63.79},{"name":"Body14","parent":"Body9","rotation":-0.04,"x":2.91,"y":6.97,"transform":"noScale","color":"abe323ff"},{"name":"Body10","parent":"Body7","rotation":0.08,"x":131.87,"y":75.17},{"name":"Body15","parent":"Body10","rotation":-0.04,"x":9.74,"y":8.31,"transform":"noScale","color":"abe323ff"},{"name":"bone6","parent":"Zong","rotation":-0.04,"x":46.97,"y":11.72},{"name":"bone7","parent":"Zong","rotation":-0.04,"x":-59.13,"y":12.06},{"name":"Attack","parent":"root"},{"name":"Glow","parent":"Attack"},{"name":"Glow2","parent":"Attack"},{"name":"Glow3","parent":"Attack"}],"slots":[{"name":"Shadow","bone":"root","color":"ffffffb0","attachment":"Shadow"},{"name":"Zhang","bone":"bone4","attachment":"Zhang"},{"name":"Hand_R","bone":"bone4","attachment":"Hand_R"},{"name":"Arm_R","bone":"Body5","attachment":"Arm_R"},{"name":"Body","bone":"root","attachment":"Body"},{"name":"Feet_R","bone":"bone7","attachment":"Feet_R"},{"name":"Feet_L","bone":"bone6","attachment":"Feet_L"},{"name":"Arm_L","bone":"Body3","attachment":"Arm_L"},{"name":"Head","bone":"Body7","attachment":"Head"},{"name":"Eye_R","bone":"Body10","attachment":"Eye_R"},{"name":"Eye_L","bone":"Body9","attachment":"Eye_L"},{"name":"Eye_R_1","bone":"Body15"},{"name":"Eye_L_1","bone":"Body14"},{"name":"Glow","bone":"Glow"},{"name":"BoWen","bone":"Glow2","blend":"additive"},{"name":"Dian","bone":"Glow3","blend":"additive"}],"transform":[{"name":"Eye_L","bones":["Body9"],"target":"Body8","rotation":0.04,"x":26.47,"y":-92.29,"rotateMix":0,"translateMix":0.3,"scaleMix":0,"shearMix":0},{"name":"Eye_R","order":1,"bones":["Body10"],"target":"Body8","rotation":0.04,"x":30.6,"y":46.67,"rotateMix":0,"translateMix":0.3,"scaleMix":0,"shearMix":0},{"name":"Zhang","order":2,"bones":["bone4"],"target":"Body5b","rotation":-74.14,"x":101.14,"y":-13.79,"shearY":-360,"rotateMix":0,"translateMix":0.8,"scaleMix":0,"shearMix":0}],"skins":[{"name":"default","attachments":{"Arm_L":{"Arm_L":{"type":"mesh","uvs":[0.26406,0,0.53835,0.13041,0.76479,0.34667,0.90756,0.52776,0.99999,0.7427,0.72473,1,0.22559,0.97246,0.1712,0.7771,0.11085,0.60491,0.01799,0.37019,1.0E-5,0.18699,0.06166,0.02854,0.19393,0.11036,0.33773,0.26186,0.45071,0.45727,0.56883,0.6966],"triangles":[14,1,2,14,8,9,15,14,2,15,2,3,8,14,15,15,3,4,7,8,15,6,7,15,5,15,4,6,15,5,12,11,0,13,12,0,10,11,12,1,13,0,13,9,10,13,10,12,14,13,1,14,9,13],"vertices":[1,6,2.43,19.56,1,2,6,35.62,35.99,0.87237,7,-29.37,32.11,0.12763,2,6,75.35,41.05,0.12811,7,9.23,42.82,0.87189,2,6,105.49,40.74,2.3E-4,7,39.1,46.83,0.99977,1,7,70.53,43.45,1,1,7,87.94,-1.41,1,1,7,58.41,-52.51,1,2,6,84.5,-50.33,0.02988,7,31.4,-46.3,0.97012,2,6,60.9,-42.71,0.28391,7,6.94,-42.15,0.71609,2,6,28.01,-33.34,0.89635,7,-26.95,-37.6,0.10365,2,6,5.99,-20.74,0.9988,7,-50.55,-28.28,0.0012,1,6,-7.88,-2.34,1,1,6,10.27,4.1,1,2,6,37.12,6.2,0.99648,7,-23.61,2.85,0.00352,2,6,66.89,1.88,0.0044,7,6.47,2.83,0.9956,1,7,42.26,0.67,1],"hull":12,"edges":[0,22,0,2,6,8,8,10,10,12,18,20,20,22,16,18,2,4,4,6,12,14,14,16,22,24,24,26,26,28,28,30,30,10],"width":59,"height":69}},"Arm_R":{"Arm_R":{"type":"mesh","uvs":[0.85334,0.03996,1,0.22988,0.98965,0.49766,0.80304,0.70029,0.50115,0.84615,0.1964,0.93069,0.08606,0.54859,0.04784,0.14579,0.32653,0.14259,0.60329,0.0945,0.6882,0.34865,0.4176,0.45047],"triangles":[11,8,9,6,7,8,6,8,11,3,4,11,5,6,11,4,5,11,10,9,0,10,0,1,11,9,10,2,10,1,3,10,2,3,11,10],"vertices":[2,8,1.93,-27.84,0.99773,9,-61.03,-37.61,0.00227,1,8,-6.91,4.22,1,2,8,9.78,35.41,0.99309,9,-62.94,26.1,0.00691,2,8,46.42,47.48,0.73945,9,-28.57,43.63,0.26055,2,8,95.31,45.37,0.04594,9,20.07,49.01,0.95406,1,9,66.76,46.52,1,1,9,67.86,-6.52,1,1,9,57.89,-59.06,1,2,8,78.55,-49.61,0.07216,9,18.02,-47.42,0.92784,2,8,38.63,-37.48,0.77484,9,-23.28,-41.53,0.22516,2,8,41.75,-1.76,0.99666,9,-25.66,-5.75,0.00334,1,9,16.83,-4.59,1],"hull":10,"edges":[0,18,0,2,2,4,4,6,6,8,8,10,10,12,12,14,14,16,16,18,2,20,20,22,22,12],"width":74,"height":66}},"BoWen":{"BoWen":{"width":128,"height":128}},"Body":{"Body":{"type":"mesh","uvs":[0.71796,0.00272,0.86934,0.06482,0.94342,0.25052,0.95689,0.45725,0.96258,0.71294,0.96506,0.90866,0.75761,0.91058,0.54149,0.91258,0.30274,0.91479,0.0972,0.89166,0.10487,0.6608,0.11312,0.47935,0.12002,0.28469,0.13771,0.14751,0.2887,0.04145,0.51222,1.0E-5,0.51652,0.13406,0.52169,0.29512,0.52724,0.46833,0.53267,0.63748,0.53716,0.7775],"triangles":[19,11,18,18,12,17,18,11,12,17,12,14,17,14,16,14,12,13,3,18,2,2,18,1,0,1,17,19,18,3,1,18,17,17,16,0,14,15,16,16,15,0,9,10,8,8,10,19,8,20,7,8,19,20,11,19,10,7,20,6,5,6,4,4,6,19,6,20,19,19,3,4],"vertices":[1,5,135.41,-66.35,1,2,4,200.58,-105.72,0.00108,5,119.57,-105.8,0.99892,2,4,155.58,-124.18,0.03949,5,74.56,-124.23,0.96051,2,4,105.9,-126.59,0.20669,5,24.87,-126.61,0.79331,2,4,44.52,-126.69,0.5829,5,-36.51,-126.67,0.4171,3,4,-2.46,-126.27,0.66055,5,-83.49,-126.21,0.25945,16,79.34,-11.43,0.08,3,4,-1.68,-71.72,0.79446,5,-82.67,-71.66,0.17354,16,24.78,-11.85,0.032,2,4,-0.87,-14.88,0.99219,5,-81.81,-14.82,0.00781,2,4,0.03,47.9,0.96,17,11.25,-13.04,0.04,3,4,6.81,101.82,0.88456,5,-74.04,101.87,0.00344,17,-42.81,-7.45,0.112,2,4,62.16,98.54,0.83726,5,-18.7,98.56,0.16274,2,4,105.65,95.38,0.49114,5,24.78,95.36,0.50886,2,4,152.31,92.5,0.1666,5,71.45,92.45,0.8334,2,4,185.12,87.11,0.07088,5,104.25,87.03,0.92912,2,4,209.66,46.83,0.01203,5,128.76,46.73,0.98797,1,5,137.33,-12.27,1,1,5,105.14,-12.65,1,1,5,66.46,-13.1,1,1,5,24.87,-13.58,1,2,4,65.19,-14.07,0.88766,5,-15.75,-14.05,0.11234,2,4,31.57,-14.48,0.98265,5,-49.37,-14.45,0.01735],"hull":16,"edges":[2,4,4,6,6,8,16,18,28,30,2,0,0,30,26,28,8,10,24,26,22,24,18,20,20,22,10,12,12,14,14,16,32,30,34,32,36,34,38,36,14,40,40,38],"width":131,"height":120}},"Dian":{"Dian":{"width":64,"height":64}},"Eye_L":{"Eye_L":{"type":"mesh","uvs":[1,1,0,1,0,0,1,0],"triangles":[1,2,3,1,3,0],"vertices":[-20.78,-59.99,-20.2,54.01,52.8,53.63,52.22,-60.37],"hull":4,"edges":[0,2,2,4,4,6,0,6],"width":57,"height":36}},"Eye_L_1":{"Eye_L_1":{"type":"mesh","uvs":[1,1,0,1,0,0,1,0],"triangles":[1,2,3,1,3,0],"vertices":[-69.65,-69.77,-69.05,66.23,65.95,65.63,65.35,-70.37],"hull":4,"edges":[0,2,2,4,4,6,0,6],"width":68,"height":67}},"Eye_R":{"Eye_R":{"type":"mesh","uvs":[1,1,0,1,0,0,1,0],"triangles":[1,2,3,1,3,0],"vertices":[-22.18,-36.96,-21.78,40.04,55.21,39.65,54.82,-37.35],"hull":4,"edges":[0,2,2,4,4,6,0,6],"width":38,"height":38}},"Eye_R_1":{"Eye_R_1":{"type":"mesh","uvs":[1,1,0,1,0,0,1,0],"triangles":[1,2,3,1,3,0],"vertices":[-60.98,-66.16,-60.43,58.84,64.57,58.29,64.01,-66.71],"hull":4,"edges":[0,2,2,4,4,6,0,6],"width":62,"height":62}},"Feet_L":{"Feet_L":{"type":"mesh","uvs":[1,1,0,1,0,0,1,0],"triangles":[1,2,3,1,3,0],"vertices":[17.53,-14.31,-16.47,-14.28,-16.45,14.72,17.55,14.69],"hull":4,"edges":[0,2,2,4,4,6,0,6],"width":17,"height":14}},"Feet_R":{"Feet_R":{"type":"mesh","uvs":[1,1,0,1,0,0,1,0],"triangles":[1,2,3,1,3,0],"vertices":[17.63,-13.5,-16.37,-13.47,-16.35,17.53,17.65,17.5],"hull":4,"edges":[0,2,2,4,4,6,0,6],"width":17,"height":15}},"Glow":{"Glow":{"width":128,"height":128}},"Hand_R":{"Hand_R":{"type":"mesh","uvs":[1,1,0,1,0,0,1,0],"triangles":[1,2,3,1,3,0],"vertices":[-31.22,-6.25,-5.81,33.29,34.57,7.34,9.16,-32.2],"hull":4,"edges":[0,2,2,4,4,6,0,6],"width":23,"height":24}},"Head":{"Head":{"type":"mesh","uvs":[0.39928,0.05916,0.58132,0.07843,0.65486,0.03519,0.7425,0.06048,0.81984,0.1561,0.88065,0.25044,0.96547,0.24326,0.99583,0.28463,0.99383,0.33453,0.95083,0.36728,0.91161,0.33087,0.84766,0.33059,0.79298,0.45633,0.73365,0.58134,0.76893,0.61736,0.77119,0.68751,0.72791,0.74926,0.65421,0.7778,0.61501,0.93022,0.53713,0.86423,0.40496,0.93935,0.27485,0.99294,0.20134,0.93217,0.15718,0.86574,0.12422,0.89922,0.07555,0.75581,0.09321,0.58423,0.10791,0.44134,0.1231,0.29375,0.05236,0.29336,0,0.25862,0.05074,0.22519,0.13509,0.22279,0.16339,0.11644,0.23562,0.02988,0.32688,0.01069,0.52957,0.45413,0.30806,0.48597,0.17416,0.57445,0.48101,0.57445,0.16579,0.73518,0.46288,0.75877,0.32201,0.79268,0.30387,0.63195],"triangles":[28,29,31,30,31,29,32,28,31,11,4,5,10,5,6,10,6,7,11,5,10,8,10,7,9,10,8,36,0,1,34,35,0,0,33,34,0,32,33,36,32,0,28,32,36,27,28,36,4,1,3,11,1,4,37,27,36,1,2,3,1,11,36,12,36,11,38,27,37,39,37,36,13,36,12,39,36,13,26,27,38,43,38,37,43,37,39,40,26,38,40,38,43,13,17,39,15,16,13,15,13,14,25,26,40,41,43,39,17,41,39,13,16,17,42,43,41,40,43,42,19,41,17,23,25,40,23,40,42,24,25,23,18,19,17,22,23,42,20,42,41,20,41,19,21,22,42,20,21,42],"vertices":[2,10,384.53,-40.07,0.95,11,283.18,-68.76,0.05,2,10,375.1,-130.88,0.95,11,273.68,-159.56,0.05,2,10,395.38,-167.65,0.95,11,293.93,-196.34,0.05,2,10,383.28,-211.34,0.95,11,281.8,-240.02,0.05,2,10,338,-249.77,0.95,11,236.5,-278.42,0.05,2,10,293.36,-279.94,0.95,11,191.84,-308.56,0.05,2,10,296.6,-322.28,0.95,11,195.04,-350.9,0.05,2,10,277.01,-337.36,0.95,11,175.45,-365.96,0.05,2,10,253.47,-336.27,0.95,11,151.9,-364.86,0.05,2,10,238.09,-314.76,0.95,11,136.54,-343.34,0.05,2,10,255.35,-295.25,0.95,11,153.81,-323.84,0.05,2,10,255.59,-263.34,0.95,11,154.08,-291.93,0.05,2,10,196.34,-235.84,0.95,11,94.85,-264.38,0.05,2,10,137.45,-206.01,0.9,11,35.98,-234.52,0.1,2,10,120.38,-223.56,0.95,11,18.9,-252.05,0.05,2,10,87.27,-224.56,0.95,11,-14.22,-253.03,0.05,2,10,58.21,-202.86,0.95,11,-43.26,-231.31,0.05,2,10,44.87,-166.03,0.95,11,-56.57,-194.47,0.05,2,10,-27,-146.21,0.95,11,-128.43,-174.59,0.05,2,10,4.29,-107.46,0.95,11,-97.11,-135.87,0.05,2,10,-30.92,-41.38,0.95,11,-132.27,-69.76,0.05,2,10,-55.98,23.64,0.95,11,-157.28,-4.72,0.05,2,10,-27.16,60.22,0.95,11,-128.44,31.83,0.05,2,10,4.28,82.14,0.95,11,-96.98,53.73,0.05,2,10,-11.47,98.64,0.95,11,-112.72,70.25,0.05,2,10,56.31,122.68,0.95,11,-44.92,94.23,0.05,2,10,137.26,113.57,0.95,11,36.03,85.06,0.05,2,10,204.68,105.98,0.9,11,103.44,77.43,0.1,2,10,274.31,98.15,0.95,11,173.06,69.54,0.05,2,10,274.63,133.45,0.95,11,173.41,104.84,0.05,2,10,291.12,159.51,0.95,11,189.92,130.9,0.05,2,10,306.81,134.13,0.95,11,205.59,105.5,0.05,2,10,307.79,92.04,0.95,11,206.53,63.41,0.05,2,10,357.93,77.73,0.95,11,256.67,49.07,0.05,2,10,398.65,41.54,0.95,11,297.36,12.85,0.05,2,10,407.54,-4.03,0.95,11,306.22,-32.73,0.05,2,10,197.87,-104.4,0.9,11,96.47,-132.95,0.1,2,10,183.25,6.19,0.74,11,81.93,-22.35,0.26,2,10,141.73,73.16,0.74,11,40.47,44.65,0.26,2,10,141.17,-79.96,0.74,11,39.79,-108.47,0.26,2,10,65.88,77.61,0.74,11,-35.38,49.16,0.26,2,10,54.2,-70.59,0.74,11,-47.17,-99.04,0.26,2,10,38.45,-0.24,0.74,11,-62.87,-28.67,0.26,2,10,114.35,8.53,0.74,11,13.04,-19.96,0.26],"hull":36,"edges":[22,24,48,50,56,58,58,60,68,70,0,70,0,2,2,4,4,6,6,8,8,10,10,12,12,14,18,20,20,22,14,16,16,18,24,26,26,28,28,30,30,32,32,34,34,36,36,38,38,40,40,42,46,48,42,44,44,46,54,56,50,52,52,54,60,62,66,68,62,64,64,66,54,72,72,26],"width":249,"height":236}},"Shadow":{"Shadow":{"scaleX":6.0016,"scaleY":1.1138,"width":32,"height":32}},"Zhang":{"Zhang":{"type":"mesh","uvs":[1,1,0,1,0,0,1,0],"triangles":[1,2,3,1,3,0],"vertices":[-127.78,11.82,-23.43,174.19,240.72,4.42,136.37,-157.94],"hull":4,"edges":[0,2,2,4,4,6,0,6],"width":96,"height":157}}}}],"events":{"Guide":{},"OnSKillCast":{},"PlayEffect":{}},"animations":{"Attack":{"bones":{"bone4":{"rotate":[{"angle":-20.88,"curve":0.25,"c3":0.75},{"time":0.1333,"angle":-112.83,"curve":0.25,"c3":0.75},{"time":0.2,"angle":39.24,"curve":0.25,"c3":0.75},{"time":0.3,"angle":43.7,"curve":0.25,"c3":0.75},{"time":0.4,"angle":21.37,"curve":0.25,"c3":0.75},{"time":0.6,"angle":-20.88}],"translate":[{"x":-89.2,"y":-1.14,"curve":0.25,"c3":0.75},{"time":0.1333,"x":275.58,"y":-36,"curve":0.25,"c3":0.75},{"time":0.2,"x":-205.89,"y":70.68,"curve":"stepped"},{"time":0.3333,"x":-205.89,"y":70.68,"curve":0.25,"c3":0.75},{"time":0.6,"x":-89.2,"y":-1.14}]},"Body":{"rotate":[{"angle":-0.04,"curve":0.25,"c3":0.75},{"time":0.1333,"angle":-7.66,"curve":0.25,"c3":0.75},{"time":0.2,"angle":8.57,"curve":"stepped"},{"time":0.3333,"angle":8.57,"curve":0.25,"c3":0.75},{"time":0.6,"angle":-0.04}],"scale":[{"x":1.002,"y":0.998,"curve":0.25,"c3":0.75},{"time":0.1333,"x":1.1,"y":0.9,"curve":0.25,"c3":0.75},{"time":0.2,"x":0.95,"y":1.05,"curve":0.25,"c3":0.75},{"time":0.3333,"x":1.002,"y":0.998}]},"Body7":{"rotate":[{"curve":0.382,"c2":0.58,"c3":0.731},{"time":0.1,"angle":-0.02,"curve":"stepped"},{"time":0.1667,"angle":-0.02,"curve":0.25,"c3":0.75},{"time":0.3,"angle":0.05,"curve":"stepped"},{"time":0.4,"angle":0.05,"curve":0.243,"c3":0.655,"c4":0.63},{"time":0.6}],"scale":[{"curve":0.25,"c3":0.75},{"time":0.1333,"x":1.05,"y":0.95,"curve":0.25,"c3":0.75},{"time":0.2,"x":0.95,"y":1.05,"curve":0.25,"c3":0.75},{"time":0.3333}]},"Body8":{"translate":[{"curve":0.25,"c3":0.75},{"time":0.1333,"x":46.51,"y":13.09,"curve":0.25,"c3":0.75},{"time":0.2,"x":-9.49,"y":6.45,"curve":"stepped"},{"time":0.3333,"x":-9.49,"y":6.45,"curve":0.25,"c3":0.75},{"time":0.6}]},"Body2":{"rotate":[{"angle":1.25,"curve":0.375,"c2":0.62,"c3":0.716},{"time":0.0667,"curve":0.25,"c3":0.75},{"time":0.1667,"angle":12.12,"curve":0.25,"c3":0.75},{"time":0.2667,"angle":9.57,"curve":"stepped"},{"time":0.4,"angle":9.57,"curve":0.243,"c3":0.68,"c4":0.71},{"time":0.6,"angle":1.25}],"translate":[{"x":0.11,"y":0.65,"curve":0.36,"c2":0.64,"c3":0.695},{"time":0.0333,"curve":0.25,"c3":0.75},{"time":0.1333,"x":17.2,"y":1.93,"curve":0.25,"c3":0.75},{"time":0.2333,"x":2.65,"y":15.31,"curve":"stepped"},{"time":0.3667,"x":2.65,"y":15.31,"curve":0.245,"c3":0.711,"c4":0.83},{"time":0.6,"x":0.11,"y":0.65}],"scale":[{"curve":0.25,"c3":0.75},{"time":0.1333,"x":1.1,"y":0.9,"curve":0.25,"c3":0.75},{"time":0.2,"x":0.95,"y":1.05,"curve":0.25,"c3":0.75},{"time":0.3333}]},"Body3":{"rotate":[{"angle":1.29,"curve":"stepped"},{"time":0.1333,"angle":1.29,"curve":0.25,"c3":0.75},{"time":0.2,"angle":16.9,"curve":"stepped"},{"time":0.3333,"angle":16.9,"curve":0.25,"c3":0.75},{"time":0.6,"angle":1.29}]},"Body5":{"rotate":[{"curve":0.25,"c3":0.75},{"time":0.1333,"angle":-92.71,"curve":0.25,"c3":0.75},{"time":0.2,"angle":-19.03,"curve":"stepped"},{"time":0.3333,"angle":-19.03,"curve":0.25,"c3":0.75},{"time":0.6}],"translate":[{"curve":0.25,"c3":0.75},{"time":0.1333,"x":7.82,"y":32.29,"curve":0.25,"c3":0.75},{"time":0.2,"x":4.47,"y":12.66}]},"Body5b":{"rotate":[{"curve":0.25,"c3":0.75},{"time":0.1333,"angle":-23.63,"curve":0.25,"c3":0.75},{"time":0.2,"angle":-1.6,"curve":0.25,"c3":0.75},{"time":0.6}],"translate":[{"curve":0.25,"c3":0.75},{"time":0.1333,"x":9.97,"y":-4.56,"curve":0.25,"c3":0.75},{"time":0.2}]},"Zong":{"translate":[{"curve":0.25,"c3":0.75},{"time":0.1333,"x":90.69,"curve":0.25,"c3":0.75},{"time":0.2,"x":-114.57,"curve":"stepped"},{"time":0.3333,"x":-114.57,"curve":0.25,"c3":0.75},{"time":0.6}]},"Zong_Y":{"translate":[{"curve":0.25,"c3":0.75},{"time":0.1333,"x":0.03,"y":21.91,"curve":0.25,"c3":0.75},{"time":0.2,"x":0.03,"y":20.95,"curve":"stepped"},{"time":0.3333,"x":0.03,"y":20.95,"curve":0.25,"c3":0.75},{"time":0.6}]},"bone7":{"translate":[{"x":-2.83,"curve":0.25,"c3":0.75},{"time":0.1333,"x":-60.35,"y":0.09,"curve":0.25,"c3":0.75},{"time":0.2,"x":-25.61,"y":0.04,"curve":"stepped"},{"time":0.3333,"x":-25.61,"y":0.04,"curve":0.25,"c3":0.75},{"time":0.6,"x":-2.83}]},"bone6":{"translate":[{"x":-2.83,"curve":0.25,"c3":0.75},{"time":0.1333,"x":49.21,"y":-0.07,"curve":0.25,"c3":0.75},{"time":0.2,"x":72.94,"y":-0.11,"curve":"stepped"},{"time":0.3333,"x":72.94,"y":-0.11,"curve":0.25,"c3":0.75},{"time":0.6,"x":-2.83}]},"Body3b":{"rotate":[{"time":0.1333,"curve":0.25,"c3":0.75},{"time":0.2,"angle":35.77,"curve":"stepped"},{"time":0.3333,"angle":35.77,"curve":0.25,"c3":0.75},{"time":0.6}]},"Attack":{"translate":[{"time":0.2,"x":-489.62,"y":163.21}]}}},"Dead":{"bones":{"bone4":{"translate":[{},{"time":0.1333,"y":44.09},{"time":0.2,"x":-56.14,"y":243.69},{"time":0.2667,"x":-164.88,"y":321.4},{"time":0.3333,"x":-310.18,"y":447.07},{"time":0.4,"x":-455.48,"y":465.61},{"time":0.4667,"x":-631.8,"y":425.63},{"time":0.5333,"x":-808.13,"y":270.86},{"time":0.6,"x":-897.81,"y":165.63},{"time":0.6667,"x":-962.63,"y":-99.52},{"time":1.0333,"x":-1008.32,"y":-96.48}]},"Body":{"rotate":[{"angle":-0.04,"curve":0.25,"c3":0.75},{"time":0.1333,"angle":-4.73,"curve":0.25,"c3":0.75},{"time":0.2333,"angle":16.82,"curve":0.25,"c3":0.75},{"time":0.3667,"angle":15.35},{"time":0.5,"angle":8.33},{"time":0.6333,"angle":7.99}],"scale":[{"x":1.002,"y":0.998,"curve":0.36,"c2":0.64,"c3":0.695},{"time":0.1333,"x":0.9,"y":1.1},{"time":0.2333,"curve":"stepped"},{"time":0.5},{"time":0.6333,"x":1.1,"y":0.9},{"time":0.7333}]},"Body2":{"rotate":[{},{"time":0.0333,"angle":-0.27,"curve":0.25,"c3":0.75},{"time":0.1667,"angle":-4.73,"curve":0.25,"c3":0.75},{"time":0.3,"angle":9.8,"curve":0.25,"c3":0.75},{"time":0.4,"angle":-10.91,"curve":0.25,"c3":0.75},{"time":0.5333,"angle":9.97,"curve":0.25,"c3":0.75},{"time":0.6667,"angle":-3.44,"curve":0.25,"c3":0.75},{"time":0.7667,"angle":-0.27}],"scale":[{},{"time":0.0667,"x":1.004,"y":0.996,"curve":0.369,"c2":0.63,"c3":0.706},{"time":0.2,"x":0.9,"y":1.1},{"time":0.3},{"time":0.4333,"x":1.1,"y":0.9},{"time":0.5667},{"time":0.7,"x":1.1,"y":0.9},{"time":0.8}]},"Body7":{"rotate":[{"angle":-0.02,"curve":0.25,"c3":0.75},{"time":0.1333,"angle":-5.14,"curve":0.25,"c3":0.75},{"time":0.2333,"angle":2.86},{"time":0.3667,"angle":-7.5},{"time":0.5,"angle":1.81},{"time":0.6333,"angle":-0.02}],"scale":[{"curve":0.25,"c3":0.75},{"time":0.1333,"x":0.9,"y":1.1},{"time":0.2333,"x":0.915,"y":0.915},{"time":0.3667,"x":1.05,"y":0.95},{"time":0.5},{"time":0.6333,"x":1.05,"y":0.95},{"time":0.7333}]},"Body3":{"rotate":[{"angle":0.85,"curve":0.25,"c3":0.75},{"time":0.1333,"angle":12.22},{"time":0.2333,"angle":66.77},{"time":0.3667,"angle":-52.48}]},"Body5":{"rotate":[{"angle":0.51,"curve":0.25,"c3":0.75},{"time":0.1333,"angle":-11.76},{"time":0.2333,"angle":-66.3},{"time":0.3667,"angle":-14.06}],"translate":[{},{"time":0.3667,"x":1.52,"y":-31.45}]},"Zong":{"rotate":[{"time":0.1333,"curve":0.25,"c3":0.75},{"time":0.2333,"angle":18.04,"curve":0.25,"c3":0.75},{"time":0.3667,"angle":80.83},{"time":0.5,"angle":72.38},{"time":0.6333,"angle":79.77}],"translate":[{"time":0.1333,"curve":0.25,"c3":0.75},{"time":0.2333,"x":0.16,"y":216,"curve":0.25,"c3":0.75},{"time":0.3,"x":-86.6,"y":220.08,"curve":0.25,"c3":0.75},{"time":0.3667,"x":-119.72,"y":81.25},{"time":0.4333,"x":-151.02,"y":149.1},{"time":0.5,"x":-187.53,"y":169.08},{"time":0.5667,"x":-213.07,"y":134.88},{"time":0.6333,"x":-256.86,"y":69.8},{"time":0.7333,"x":-284.81,"y":69.82}]},"Body9":{"rotate":[{"angle":0.21,"curve":"stepped"},{"time":0.4333,"angle":0.21},{"time":0.6,"angle":-24.74}],"scale":[{"time":0.4333},{"time":0.6,"x":0.544}]},"Body10":{"rotate":[{"time":0.4333},{"time":0.6,"angle":35.28}],"scale":[{"time":0.4333},{"time":0.6,"x":0.477}]}},"transform":{"Zhang":[{"rotateMix":0,"translateMix":0,"scaleMix":0,"shearMix":0}]}},"Hit":{"slots":{"Eye_L":{"attachment":[{"time":0.0667,"name":null},{"time":0.2333,"name":"Eye_L"}]},"Eye_L_1":{"attachment":[{"time":0.0667,"name":"Eye_L_1"},{"time":0.2333,"name":null}]},"Eye_R":{"attachment":[{"time":0.0667,"name":null},{"time":0.2333,"name":"Eye_R"}]},"Eye_R_1":{"attachment":[{"time":0.0667,"name":"Eye_R_1"},{"time":0.2333,"name":null}]}},"bones":{"bone4":{"rotate":[{"angle":-39.98}],"translate":[{"x":-89.2,"y":-1.14}]},"Body":{"rotate":[{"angle":-0.04,"curve":0.25,"c3":0.75},{"time":0.1667,"angle":-3.96,"curve":0.25,"c3":0.75},{"time":0.3333,"angle":-0.04}],"scale":[{"x":1.002,"y":0.998}]},"Body7":{"rotate":[{"angle":-0.02,"curve":0.25,"c3":0.75},{"time":0.1667,"angle":-3.4,"curve":0.25,"c3":0.75},{"time":0.3333,"angle":-0.02}],"translate":[{"curve":0.25,"c3":0.75},{"time":0.1667,"x":2.69,"y":-14.55,"curve":0.25,"c3":0.75},{"time":0.3333}]},"Body8":{"translate":[{"curve":0.25,"c3":0.75},{"time":0.1667,"x":32.63,"y":-26.87,"curve":0.25,"c3":0.75},{"time":0.3333}]},"Body2":{"rotate":[{"curve":0.25,"c3":0.75},{"time":0.1667,"angle":-7.88,"curve":0.25,"c3":0.75},{"time":0.3333}],"translate":[{"curve":0.25,"c3":0.75},{"time":0.1667,"x":2.49,"y":-4.37,"curve":0.25,"c3":0.75},{"time":0.3333}]},"Body3":{"rotate":[{"angle":1.29,"curve":0.25,"c3":0.75},{"time":0.1667,"angle":7.54,"curve":0.25,"c3":0.75},{"time":0.3333,"angle":1.29}]},"Body5":{"rotate":[{"angle":-0.66,"curve":0.25,"c3":0.75},{"time":0.1667,"angle":-39.44,"curve":0.25,"c3":0.75},{"time":0.3333,"angle":-0.66}]},"bone7":{"translate":[{"curve":0.25,"c3":0.75},{"time":0.1667,"x":-21.16,"y":21.23,"curve":0.25,"c3":0.75},{"time":0.3333}]},"Zong":{"translate":[{"curve":0.25,"c3":0.75},{"time":0.0333,"x":128.25,"curve":0.25,"c3":0.75},{"time":0.3333}]}}},"Idle":{"bones":{"Body":{"rotate":[{"angle":-0.04,"curve":0.348,"c2":0.66,"c3":0.682},{"time":0.0333,"curve":0.25,"c3":0.75},{"time":0.7,"angle":-2.22,"curve":0.247,"c3":0.729,"c4":0.91},{"time":1.3333,"angle":-0.04}],"scale":[{"x":1.002,"y":0.998,"curve":0.36,"c2":0.64,"c3":0.695},{"time":0.0667,"curve":0.25,"c3":0.75},{"time":0.7333,"x":1.05,"y":0.95,"curve":0.245,"c3":0.711,"c4":0.83},{"time":1.3333,"x":1.002,"y":0.998}]},"Body7":{"rotate":[{"angle":-0.02,"curve":0.375,"c2":0.62,"c3":0.716},{"time":0.1333,"curve":0.25,"c3":0.75},{"time":0.8,"angle":-0.16,"curve":0.243,"c3":0.68,"c4":0.71},{"time":1.3333,"angle":-0.02}]},"Body8":{"translate":[{"curve":0.25,"c3":0.75},{"time":0.6667,"x":6.94,"y":-12.14,"curve":0.25,"c3":0.75},{"time":1.3333}]},"Body2":{"translate":[{},{"time":0.3333,"x":2.8,"y":6.56},{"time":0.6667,"x":5.61},{"time":1,"x":2.81,"y":-7.24},{"time":1.3333}]},"Body3":{"rotate":[{"angle":1.29,"curve":0.379,"c2":0.6,"c3":0.724},{"time":0.1667,"curve":0.25,"c3":0.75},{"time":0.8333,"angle":6.97,"curve":0.242,"c3":0.667,"c4":0.67},{"time":1.3333,"angle":1.29}]},"Body5":{"rotate":[{"curve":0.25,"c3":0.75},{"time":0.6667,"angle":22.78,"curve":0.25,"c3":0.75},{"time":1.3333}]},"Body5b":{"rotate":[{"curve":0.25,"c3":0.75},{"time":0.6667,"angle":-42.03,"curve":0.25,"c3":0.75},{"time":1.3333}]},"bone4":{"rotate":[{"angle":-22.85},{"time":0.6667,"angle":-29.62},{"time":1.3333,"angle":-22.85}],"translate":[{"x":-45.81},{"time":0.6667,"x":-27.33},{"time":1.3333,"x":-45.81}]}},"transform":{"Zhang":[{"rotateMix":0,"translateMix":0,"scaleMix":0,"shearMix":0}]}},"Run":{"bones":{"bone4":{"rotate":[{"angle":1.69,"curve":0.25,"c3":0.75},{"time":0.2333,"angle":-18.84,"curve":0.25,"c3":0.75},{"time":0.5,"angle":1.69}],"translate":[{"x":-102.77,"y":111.68,"curve":0.25,"c3":0.75},{"time":0.2333,"x":-70.65,"y":166.6,"curve":0.25,"c3":0.75},{"time":0.5,"x":-102.77,"y":111.68}]},"Body":{"rotate":[{"angle":6.65,"curve":0.25,"c3":0.75},{"time":0.1333,"angle":10.54,"curve":0.25,"c3":0.75},{"time":0.2333,"angle":6.65,"curve":0.25,"c3":0.75},{"time":0.3667,"angle":10.54,"curve":0.25,"c3":0.75},{"time":0.5,"angle":6.65}],"translate":[{"x":-19.02,"y":81.55,"curve":0.25,"c3":0.75},{"time":0.1333,"x":0.02,"y":15.28,"curve":0.25,"c3":0.75},{"time":0.2333,"x":-19.02,"y":81.55,"curve":0.25,"c3":0.75},{"time":0.3667,"x":0.02,"y":15.28,"curve":0.25,"c3":0.75},{"time":0.5,"x":-19.02,"y":81.55}],"scale":[{"x":1.05,"y":0.95,"curve":0.25,"c3":0.75},{"time":0.1333,"x":0.95,"y":1.05,"curve":0.25,"c3":0.75},{"time":0.2333,"x":1.05,"y":0.95,"curve":0.25,"c3":0.75},{"time":0.3667,"x":0.95,"y":1.05,"curve":0.25,"c3":0.75},{"time":0.5,"x":1.05,"y":0.95}]},"Body2":{"rotate":[{"angle":-0.27,"curve":0.25,"c3":0.75},{"time":0.1333,"angle":-12.56,"curve":0.25,"c3":0.75},{"time":0.2333,"angle":-0.27,"curve":0.25,"c3":0.75},{"time":0.3667,"angle":-12.56,"curve":0.25,"c3":0.75},{"time":0.5,"angle":-0.27}],"scale":[{"x":1.05,"y":0.95,"curve":0.25,"c3":0.75},{"time":0.1333,"x":0.95,"y":1.05,"curve":0.25,"c3":0.75},{"time":0.2333,"x":1.05,"y":0.95,"curve":0.25,"c3":0.75},{"time":0.3667,"x":0.95,"y":1.05,"curve":0.25,"c3":0.75},{"time":0.5,"x":1.05,"y":0.95}]},"Body7":{"rotate":[{"angle":0.88,"curve":0.375,"c2":0.62,"c3":0.716},{"time":0.0333,"angle":1.46,"curve":0.375,"c2":0.62,"c3":0.716},{"time":0.1333,"angle":-2.97,"curve":0.25,"c3":0.75},{"time":0.2667,"angle":1.46,"curve":0.25,"c3":0.75},{"time":0.4,"angle":-2.97,"curve":0.243,"c3":0.68,"c4":0.71},{"time":0.5,"angle":0.88}],"translate":[{"curve":0.25,"c3":0.75},{"time":0.1333,"x":-0.17,"y":15.93,"curve":0.25,"c3":0.75},{"time":0.2333,"curve":0.25,"c3":0.75},{"time":0.3667,"x":-0.17,"y":15.93,"curve":0.25,"c3":0.75},{"time":0.5}],"scale":[{"x":1.013,"y":0.987,"curve":0.381,"c2":0.55,"c3":0.742},{"time":0.0333,"x":1.05,"y":0.95,"curve":0.25,"c3":0.75},{"time":0.1667,"x":0.95,"y":1.05,"curve":0.25,"c3":0.75},{"time":0.3,"x":1.05,"y":0.95,"curve":0.25,"c3":0.75},{"time":0.4333,"x":0.95,"y":1.05,"curve":0.245,"c3":0.637,"c4":0.56},{"time":0.5,"x":1.013,"y":0.987}]},"Body8":{"translate":[{"x":-8.1,"y":1.15,"curve":0.25,"c3":0.75},{"time":0.1333,"x":9.2,"y":-8.01,"curve":0.25,"c3":0.75},{"time":0.2333,"x":-8.1,"y":1.15,"curve":0.25,"c3":0.75},{"time":0.3667,"x":9.21,"y":-0.01,"curve":0.25,"c3":0.75},{"time":0.5,"x":-8.1,"y":1.15}]},"Body3":{"rotate":[{"angle":0.85,"curve":0.25,"c3":0.75},{"time":0.2333,"angle":29.63,"curve":0.25,"c3":0.75},{"time":0.5,"angle":0.85}],"translate":[{"x":4.77,"y":35.43,"curve":0.25,"c3":0.75},{"time":0.2333,"x":-0.64,"y":-4.72,"curve":0.25,"c3":0.75},{"time":0.5,"x":4.77,"y":35.43}]},"Body5":{"rotate":[{"angle":0.51,"curve":0.25,"c3":0.75},{"time":0.2333,"angle":-22.26,"curve":0.25,"c3":0.75},{"time":0.5,"angle":0.51}]},"bone7":{"translate":[{"x":-41.09,"y":71.2,"curve":0.25,"c3":0.75},{"time":0.1333,"x":57.52,"y":-0.04,"curve":0.25,"c3":0.75},{"time":0.2333,"x":173.6,"y":77.92,"curve":0.25,"c3":0.75},{"time":0.3667,"x":72.02,"y":8.42,"curve":0.25,"c3":0.75},{"time":0.5,"x":-41.09,"y":71.2}]},"bone6":{"translate":[{"x":34.02,"y":69.83,"curve":0.25,"c3":0.75},{"time":0.1333,"x":-88.4,"y":0.13,"curve":0.25,"c3":0.75},{"time":0.2333,"x":-174.57,"y":61.73,"curve":0.25,"c3":0.75},{"time":0.3667,"x":-86.13,"y":0.13,"curve":0.25,"c3":0.75},{"time":0.5,"x":34.02,"y":69.83}]}}},"Skill_1":{"slots":{"BoWen":{"color":[{"color":"ffffffff"},{"time":0.1667,"color":"4fd4ff7f"},{"time":0.3333,"color":"4fd4ff00"}],"attachment":[{"name":"BoWen"}]},"Dian":{"color":[{"time":0.1,"color":"ffffffff"},{"time":0.1667,"color":"ffffff00"}],"attachment":[{"name":"Dian"}]},"Glow":{"color":[{"color":"4888ffff","curve":0.25,"c4":0.65},{"time":0.3333,"color":"0059ff00"}],"attachment":[{"name":"Glow"}]}},"bones":{"bone4":{"rotate":[{"angle":32,"curve":0.25,"c3":0.75},{"time":0.1,"angle":-5.15,"curve":0.25,"c3":0.75},{"time":0.3333,"angle":44.3,"curve":0.25,"c3":0.75},{"time":0.4333,"angle":31.06,"curve":0.25,"c3":0.75},{"time":0.6667,"angle":-20.88}],"translate":[{"x":-89.2,"y":117.09,"curve":0.25,"c3":0.75},{"time":0.1,"x":-45.82,"y":200.44,"curve":0.25,"c3":0.75},{"time":0.3333,"x":-77.56,"y":125.21,"curve":"stepped"},{"time":0.4333,"x":-77.56,"y":125.21,"curve":0.25,"c3":0.75},{"time":0.6667,"x":-89.2,"y":-1.14}]},"Body":{"rotate":[{"angle":8.38,"curve":"stepped"},{"time":0.4333,"angle":8.38,"curve":0.25,"c3":0.75},{"time":0.6667,"angle":-0.04}]},"Body7":{"rotate":[{"angle":-0.02}],"translate":[{"x":-15.72,"y":-25.38,"curve":0.25,"c3":0.75},{"time":0.3333,"x":-0.4,"y":-25.69,"curve":"stepped"},{"time":0.4333,"x":-0.4,"y":-25.69,"curve":0.25,"c3":0.75},{"time":0.6667}]},"Body8":{"translate":[{"x":-48.12,"y":34.98,"curve":0.25,"c3":0.75},{"time":0.3333,"x":-24.08,"y":34.99,"curve":"stepped"},{"time":0.4333,"x":-24.08,"y":34.99,"curve":0.25,"c3":0.75},{"time":0.6667}]},"Body2":{"rotate":[{"angle":3.66,"curve":"stepped"},{"time":0.5,"angle":3.66,"curve":0.243,"c3":0.658,"c4":0.64},{"time":0.6667,"angle":0.82}],"translate":[{"x":-4.33,"y":17.64,"curve":0.375,"c2":0.62,"c3":0.716},{"time":0.0333,"x":-5.44,"y":17.57,"curve":0.25,"c3":0.75},{"time":0.1333,"x":3.26,"y":-11.12,"curve":0.25,"c3":0.75},{"time":0.3667,"x":3.08,"y":18.12,"curve":"stepped"},{"time":0.4667,"x":3.08,"y":18.12,"curve":0.244,"c3":0.697,"c4":0.78},{"time":0.6667,"x":0.24,"y":1.4}]},"Body3":{"rotate":[{"angle":34.63,"curve":"stepped"},{"time":0.4333,"angle":34.63,"curve":0.25,"c3":0.75},{"time":0.6667,"angle":1.29}]},"Body5":{"rotate":[{"angle":-37.86,"curve":0.25,"c3":0.75},{"time":0.1,"angle":-42.53,"curve":0.25,"c3":0.75},{"time":0.3333,"angle":-37.87,"curve":"stepped"},{"time":0.4333,"angle":-37.87,"curve":0.25,"c3":0.75},{"time":0.6667}],"translate":[{"x":-4.61,"y":27.37}]},"Body5b":{"rotate":[{"angle":18.56,"curve":0.25,"c3":0.75},{"time":0.1,"angle":-10.17,"curve":0.25,"c3":0.75},{"time":0.3333,"angle":25.67,"curve":"stepped"},{"time":0.4333,"angle":25.67,"curve":0.25,"c3":0.75},{"time":0.6667}]},"Zong":{"translate":[{"x":-21.27,"curve":0.25,"c3":0.75},{"time":0.1,"x":68.34,"y":0.03,"curve":"stepped"},{"time":0.4333,"x":68.34,"y":0.03,"curve":0.25,"c3":0.75},{"time":0.6667}]},"Zong_Y":{"translate":[{"x":0.04,"y":19.32,"curve":0.25,"c3":0.75},{"time":0.1,"y":14.33,"curve":0.25,"c3":0.75},{"time":0.3333,"y":24.76,"curve":"stepped"},{"time":0.4333,"y":24.76,"curve":0.25,"c3":0.75},{"time":0.6667}]},"bone7":{"translate":[{"x":-15.35,"y":0.02,"curve":"stepped"},{"time":0.4333,"x":-15.35,"y":0.02,"curve":0.25,"c3":0.75},{"time":0.6667}]},"bone6":{"translate":[{"x":65.02,"y":-0.1,"curve":"stepped"},{"time":0.4333,"x":65.02,"y":-0.1,"curve":0.25,"c3":0.75},{"time":0.6667}]},"Body3b":{"rotate":[{"angle":43.99,"curve":"stepped"},{"time":0.4333,"angle":43.99,"curve":0.25,"c3":0.75},{"time":0.6667}]},"Glow2":{"rotate":[{},{"time":0.3333,"angle":-97.62}],"scale":[{"curve":0,"c2":0.49,"c3":0.75},{"time":0.3333,"x":3,"y":3}]},"Glow":{"scale":[{"x":2,"y":2,"curve":0,"c2":0.43,"c3":0.75},{"time":0.3333,"x":5,"y":5}]},"Attack":{"translate":[{"x":-457.69,"y":219.98}]},"Glow3":{"scale":[{"curve":0,"c2":0.33,"c3":0.5,"c4":0.73},{"time":0.1,"x":4,"y":4,"curve":0.391,"c2":0.6,"c3":0.783},{"time":0.1667,"x":3,"y":3}]}},"events":[{"name":"OnSKillCast"},{"name":"PlayEffect"}]},"Skill_1_Guide":{"bones":{"bone4":{"rotate":[{"angle":-20.88,"curve":0.25,"c3":0.75},{"time":0.2667,"angle":-95.08,"curve":0.25,"c3":0.75},{"time":0.4667,"angle":44.81,"curve":0.25,"c3":0.75},{"time":0.6667,"angle":25.74,"curve":0.25,"c3":0.75},{"time":0.8333,"angle":38.95,"curve":0.25,"c3":0.75},{"time":1,"angle":32}],"translate":[{"x":-89.2,"y":-1.14,"curve":0.25,"c3":0.75},{"time":0.2667,"x":37.69,"y":253.73,"curve":0.25,"c3":0.75},{"time":0.4667,"x":-146.49,"y":104.22,"curve":0.25,"c3":0.75},{"time":0.6667,"x":-130.46,"y":124.62,"curve":0.25,"c3":0.75},{"time":1,"x":-89.2,"y":117.09}]},"Body":{"rotate":[{"angle":-0.04,"curve":0.25,"c3":0.75},{"time":0.2667,"angle":-6.37,"curve":0.25,"c3":0.75},{"time":0.4667,"angle":8.38}],"scale":[{"x":1.002,"y":0.998}]},"Body7":{"rotate":[{"angle":-0.02}],"translate":[{"curve":0.25,"c3":0.75},{"time":0.2667,"x":-0.4,"y":-25.69,"curve":"stepped"},{"time":0.4667,"x":-0.4,"y":-25.69,"curve":0.25,"c3":0.75},{"time":0.6667,"x":-15.72,"y":-25.38,"curve":0.25,"c3":0.75},{"time":0.8333,"x":-0.4,"y":-25.69,"curve":0.25,"c3":0.75},{"time":1,"x":-15.72,"y":-25.38}]},"Body8":{"translate":[{"curve":0.25,"c3":0.75},{"time":0.2667,"x":80.16,"y":-21.97,"curve":0.25,"c3":0.75},{"time":0.4667,"x":-24.08,"y":34.99,"curve":0.25,"c3":0.75},{"time":0.6667,"x":-48.12,"y":34.98,"curve":0.25,"c3":0.75},{"time":0.8333,"x":-24.08,"y":34.99,"curve":0.25,"c3":0.75},{"time":1,"x":-48.12,"y":34.98}]},"Body2":{"rotate":[{"angle":0.82,"curve":0.381,"c2":0.59,"c3":0.729},{"time":0.0667,"curve":0.25,"c3":0.75},{"time":0.3333,"angle":-11.78,"curve":0.25,"c3":0.75},{"time":0.5333,"angle":3.66}],"translate":[{"x":0.24,"y":1.4,"curve":0.367,"c2":0.63,"c3":0.705},{"time":0.0333,"curve":0.25,"c3":0.75},{"time":0.3,"x":16.58,"y":-10.5,"curve":0.25,"c3":0.75},{"time":0.5,"x":3.08,"y":18.12,"curve":0.25,"c3":0.75},{"time":0.7,"x":-5.44,"y":17.57,"curve":0.25,"c3":0.75},{"time":0.8667,"x":3.08,"y":18.12,"curve":0.243,"c3":0.68,"c4":0.71},{"time":1,"x":-4.33,"y":17.64}]},"Body3":{"rotate":[{"angle":1.29,"curve":0.25,"c3":0.75},{"time":0.2667,"angle":8.68,"curve":0.25,"c3":0.75},{"time":0.4667,"angle":34.63}]},"Body5":{"rotate":[{"curve":0.25,"c3":0.75},{"time":0.2667,"angle":-46.41,"curve":0.25,"c3":0.75},{"time":0.4667,"angle":-37.86}],"translate":[{"time":0.2667,"curve":0.25,"c3":0.75},{"time":0.4667,"x":-4.61,"y":27.37}]},"Body5b":{"rotate":[{"curve":0.25,"c3":0.75},{"time":0.2667,"angle":-10.37,"curve":0.25,"c3":0.75},{"time":0.4667,"angle":29.9,"curve":0.25,"c3":0.75},{"time":0.6667,"angle":16.22,"curve":0.25,"c3":0.75},{"time":1,"angle":18.56}]},"Zong":{"translate":[{"curve":0.25,"c3":0.75},{"time":0.2667,"x":19.32,"curve":0.25,"c3":0.75},{"time":0.4667,"x":-21.27}]},"Zong_Y":{"translate":[{"curve":0.25,"c3":0.75},{"time":0.2667,"x":0.03,"y":20.06,"curve":0.25,"c3":0.75},{"time":0.4667,"x":0.04,"y":25.18,"curve":0.25,"c3":0.75},{"time":0.6667,"x":0.04,"y":19.32,"curve":0.25,"c3":0.75},{"time":0.8333,"x":0.04,"y":31.69,"curve":0.25,"c3":0.75},{"time":1,"x":0.04,"y":19.32}]},"bone7":{"translate":[{"curve":0.25,"c3":0.75},{"time":0.2667,"x":-34.18,"y":0.05,"curve":0.25,"c3":0.75},{"time":0.4667,"x":-15.35,"y":0.02}]},"bone6":{"translate":[{"curve":0.25,"c3":0.75},{"time":0.2667,"x":28.98,"y":-0.04,"curve":0.25,"c3":0.75},{"time":0.4667,"x":65.02,"y":-0.1}]},"Body3b":{"rotate":[{"curve":0.25,"c3":0.75},{"time":0.2667,"angle":24.71,"curve":0.25,"c3":0.75},{"time":0.4667,"angle":43.99}]}},"events":[{"time":0.3333,"name":"Guide"}]}}}