{"skeleton":{"hash":"I56qc3s94us06XaBNJKWh2dLvwc","spine":"3.8.99","images":"E:/技能特效/spine资源优化/YuJin_Skill_2/YuJin_Skill_2/imager","audio":""},"bones":[{"name":"root"},{"name":"Glow","parent":"root"},{"name":"BaoDian","parent":"root"},{"name":"Fog","parent":"root"},{"name":"Wind","parent":"root"},{"name":"Rotation","parent":"Wind"},{"name":"BaoDian2","parent":"root"},{"name":"Wind2","parent":"root"},{"name":"Rotation2","parent":"Wind2"},{"name":"Wind3","parent":"root"},{"name":"Rotation3","parent":"Wind3"}],"slots":[{"name":"Glow","bone":"Glow"},{"name":"DaoGuang","bone":"Rotation","blend":"additive"},{"name":"DaoGuang2","bone":"Rotation2","blend":"additive"},{"name":"DaoGuang3","bone":"Rotation3","blend":"additive"},{"name":"BaoDian_01","bone":"BaoDian","attachment":"BaoDian_01"},{"name":"BaoDian_1","bone":"BaoDian2","blend":"additive"},{"name":"Fog_02","bone":"Fog"}],"skins":[{"name":"default","attachments":{"BaoDian_01":{"BaoDian_01":{"y":56.92,"width":64,"height":128},"BaoDian_02":{"y":56.92,"width":64,"height":128},"BaoDian_03":{"y":56.92,"width":64,"height":128},"BaoDian_04":{"y":56.92,"width":64,"height":128},"BaoDian_05":{"y":56.92,"width":64,"height":128},"BaoDian_06":{"y":56.92,"width":64,"height":128},"BaoDian_07":{"y":56.92,"width":64,"height":128},"BaoDian_08":{"y":56.92,"width":64,"height":128}},"BaoDian_1":{"BaoDian_01":{"y":56.92,"width":64,"height":128},"BaoDian_02":{"y":56.92,"width":64,"height":128},"BaoDian_03":{"y":56.92,"width":64,"height":128},"BaoDian_04":{"y":56.92,"width":64,"height":128},"BaoDian_05":{"y":56.92,"width":64,"height":128},"BaoDian_06":{"y":56.92,"width":64,"height":128},"BaoDian_07":{"y":56.92,"width":64,"height":128},"BaoDian_08":{"y":56.92,"width":64,"height":128}},"DaoGuang":{"DaoGuang":{"width":128,"height":128}},"DaoGuang2":{"DaoGuang":{"width":128,"height":128}},"DaoGuang3":{"DaoGuang":{"width":128,"height":128}},"Fog_02":{"Fog_02":{"y":31.42,"width":64,"height":64},"Fog_04":{"y":31.42,"width":64,"height":64},"Fog_06":{"y":31.42,"width":64,"height":64},"Fog_08":{"y":31.42,"width":64,"height":64},"Fog_10":{"y":31.42,"width":64,"height":64},"Fog_12":{"y":31.42,"width":64,"height":64},"Fog_15":{"y":31.42,"width":64,"height":64}},"Glow":{"Glow":{"width":64,"height":64}}}}],"animations":{"Skill":{"slots":{"BaoDian_01":{"color":[{"color":"ab3dffff"}],"attachment":[{"time":0.0667,"name":"BaoDian_02"},{"time":0.1333,"name":"BaoDian_03"},{"time":0.2,"name":"BaoDian_04"},{"time":0.2667,"name":"BaoDian_05"},{"time":0.3333,"name":"BaoDian_06"},{"time":0.4,"name":"BaoDian_07"},{"time":0.4667,"name":"BaoDian_08"},{"time":0.5333,"name":null}]},"BaoDian_1":{"color":[{"color":"ffffffff"},{"time":0.2,"color":"ab3dffff"}],"attachment":[{"name":"BaoDian_01"},{"time":0.0667,"name":"BaoDian_02"},{"time":0.1333,"name":"BaoDian_03"},{"time":0.2,"name":"BaoDian_04"},{"time":0.2667,"name":"BaoDian_05"},{"time":0.3,"name":"BaoDian_06"},{"time":0.3333,"name":"BaoDian_07"},{"time":0.3667,"name":"BaoDian_08"},{"time":0.4,"name":null}]},"DaoGuang":{"color":[{"color":"b85fff00"},{"time":0.1667,"color":"b85fffcb"},{"time":0.3333,"color":"b860ffff"},{"time":0.5,"color":"ffffff00"}],"attachment":[{"name":"DaoGuang"}]},"DaoGuang2":{"color":[{"time":0.1,"color":"b85fff00"},{"time":0.2667,"color":"b85fffcb"},{"time":0.4333,"color":"b860ffff"},{"time":0.6,"color":"ffffff00"}],"attachment":[{"time":0.1,"name":"DaoGuang"}]},"DaoGuang3":{"color":[{"time":0.2,"color":"b85fff00"},{"time":0.3667,"color":"b85fffcb"},{"time":0.5333,"color":"b860ffff"},{"time":0.7,"color":"ffffff00"}],"attachment":[{"time":0.2,"name":"DaoGuang"}]},"Fog_02":{"attachment":[{"time":0.1333,"name":"Fog_02"},{"time":0.2,"name":"Fog_04"},{"time":0.2667,"name":"Fog_06"},{"time":0.3333,"name":"Fog_08"},{"time":0.4,"name":"Fog_10"},{"time":0.4667,"name":"Fog_12"},{"time":0.5333,"name":"Fog_15"},{"time":0.6,"name":null}]},"Glow":{"color":[{"color":"7d13ffff","curve":"stepped"},{"time":0.3333,"color":"7d13ffff"},{"time":0.6667,"color":"7c12ff00"}],"attachment":[{"name":"Glow"}]}},"bones":{"BaoDian2":{"scale":[{"x":-0.663,"y":0.8}]},"Rotation":{"rotate":[{},{"time":0.1333,"angle":180},{"time":0.2667},{"time":0.4,"angle":180},{"time":0.5333}],"scale":[{"x":0.5,"y":0.5},{"time":0.5}]},"Rotation2":{"rotate":[{"time":0.1},{"time":0.2333,"angle":180},{"time":0.3667},{"time":0.5,"angle":180},{"time":0.6333}],"scale":[{"time":0.1,"x":0.3,"y":0.3},{"time":0.6,"x":0.7,"y":0.7}]},"Rotation3":{"rotate":[{"time":0.2},{"time":0.3333,"angle":180},{"time":0.4667},{"time":0.6,"angle":180},{"time":0.7,"angle":45}],"scale":[{"time":0.2,"x":0.2,"y":0.2},{"time":0.4667,"x":0.627,"y":0.627},{"time":0.7,"x":0.3,"y":0.3}]},"Glow":{"scale":[{"y":0.316,"curve":0,"c2":0.31,"c3":0.75},{"time":0.1333,"x":1.235,"y":0.487}]},"Wind":{"translate":[{},{"time":0.5,"y":127.69}],"scale":[{"y":0.487}]},"Wind2":{"translate":[{"time":0.1},{"time":0.6,"y":127.69}],"scale":[{"time":0.1,"y":0.487}]},"Wind3":{"translate":[{"time":0.2},{"time":0.7,"y":127.69}],"scale":[{"time":0.2,"y":0.487}]}}}}}