{"skeleton":{"hash":"OLdHEWt561ejdNYLJGSOVkoNSvc","spine":"3.8.99","x":-61.45,"y":-16.45,"width":122.08,"height":119.29,"images":"./images/","audio":""},"bones":[{"name":"root"},{"name":"bone","parent":"root","length":136.4,"rotation":45,"x":-40,"y":5,"scaleX":0.8,"scaleY":0.8},{"name":"bone2","parent":"root","length":136.4,"rotation":-225,"x":40,"y":5,"scaleX":0.8,"scaleY":0.8},{"name":"da","parent":"root"},{"name":"gg","parent":"root"}],"slots":[{"name":"M_Z_5","bone":"bone2","attachment":"M_Z_04"},{"name":"M_Z_4","bone":"bone","attachment":"M_Z_04"},{"name":"da (1)","bone":"da","blend":"additive"},{"name":"gg","bone":"gg","blend":"additive"}],"skins":[{"name":"default","attachments":{"M_Z_4":{"M_Z_04":{"x":67.8,"y":0.44,"rotation":-90.48,"width":72,"height":138}},"M_Z_5":{"M_Z_04":{"x":67.8,"y":0.44,"rotation":-90.48,"width":72,"height":138}},"da (1)":{"da (1)":{"x":0.5,"y":0.5,"width":240,"height":198},"da (2)":{"width":240,"height":198},"da (3)":{"width":240,"height":198},"da (4)":{"width":240,"height":198},"da (5)":{"width":240,"height":198},"da (6)":{"width":240,"height":198},"da (7)":{"width":240,"height":198}},"gg":{"gg":{"x":0.5,"width":117,"height":118}}}}],"animations":{"Hit":{"slots":{"da (1)":{"attachment":[{"time":0.3333,"name":"da (1)"},{"time":0.3667,"name":"da (2)"},{"time":0.4,"name":"da (3)"},{"time":0.4333,"name":"da (4)"},{"time":0.4667,"name":"da (5)"},{"time":0.5,"name":"da (6)"},{"time":0.5333,"name":"da (7)"},{"time":0.5667,"name":null},{"time":0.6667,"name":"da (1)"},{"time":0.7,"name":"da (2)"},{"time":0.7333,"name":"da (3)"},{"time":0.7667,"name":"da (4)"},{"time":0.8,"name":"da (5)"},{"time":0.8333,"name":"da (6)"},{"time":0.8667,"name":"da (7)"},{"time":0.9,"name":null}]},"gg":{"color":[{"time":0.4,"color":"ffffffff"},{"time":0.5333,"color":"ffffff00","curve":"stepped"},{"time":0.6667,"color":"ffffffff","curve":"stepped"},{"time":0.7333,"color":"ffffffff"},{"time":0.8667,"color":"ffffff00"}],"attachment":[{"time":0.3333,"name":"gg"},{"time":0.9,"name":null}]}},"bones":{"bone":{"rotate":[{"curve":0.042,"c2":0.09,"c3":0.75},{"time":0.2667,"angle":45,"curve":0.25,"c3":0.948,"c4":0.93},{"time":0.3333,"angle":-5,"curve":"stepped"},{"time":0.4,"angle":-5,"curve":0.071,"c2":0.1,"c3":0.75},{"time":0.6,"angle":45,"curve":0.25,"c3":0.976,"c4":0.92},{"time":0.6667}],"translate":[{"curve":0.25,"c3":0.75},{"time":0.2667,"x":-10,"y":5,"curve":0.25,"c3":0.948,"c4":0.93},{"time":0.3333,"curve":"stepped"},{"time":0.4,"curve":0.25,"c3":0.75},{"time":0.6,"x":-10,"y":5,"curve":0.25,"c3":0.976,"c4":0.92},{"time":0.6667}]},"bone2":{"rotate":[{"curve":0.09,"c2":0.09,"c3":0.75},{"time":0.2667,"angle":-45,"curve":0.25,"c3":0.948,"c4":0.93},{"time":0.3333,"angle":5,"curve":"stepped"},{"time":0.4,"angle":5,"curve":0.08,"c2":0.09,"c3":0.75},{"time":0.6,"angle":-45,"curve":0.25,"c3":0.976,"c4":0.92},{"time":0.6667}],"translate":[{"curve":0.25,"c3":0.75},{"time":0.2667,"x":10,"y":5,"curve":0.25,"c3":0.948,"c4":0.93},{"time":0.3333,"x":10,"curve":"stepped"},{"time":0.4,"x":10,"curve":0.08,"c2":0.09,"c3":0.75},{"time":0.6,"x":10,"y":5,"curve":0.25,"c3":0.976,"c4":0.92},{"time":0.6667}]},"da":{"translate":[{"time":0.3333,"x":5.29,"y":47.09}],"scale":[{"time":0.3333,"x":0.647,"y":0.647}]},"gg":{"translate":[{"time":0.3333,"x":5.32,"y":47.44}]}}},"idle":{}}}