{"skeleton":{"hash":"WdKjtbIAWQ+LmgHJGIPtLMz/F2E","spine":"3.8.99","x":-58.3,"y":-58.3,"width":116.61,"height":117.45,"images":"./images/","audio":""},"bones":[{"name":"root"},{"name":"Di","parent":"root"},{"name":"Glow1","parent":"root","scaleX":0.911,"scaleY":0.911},{"name":"Glow2","parent":"root","scaleX":0.34,"scaleY":0.34},{"name":"JinBi","parent":"root","y":5.21,"scaleX":0.93,"scaleY":0.93},{"name":"QianDai","parent":"root","rotation":-26.3,"scaleX":0.785,"scaleY":0.785},{"name":"Up","parent":"root","scaleX":0.7,"scaleY":0.7}],"slots":[{"name":"33","bone":"Di","color":"ffffff00","attachment":"33"},{"name":"Glow","bone":"Glow1","color":"ffffff00","attachment":"Glow"},{"name":"Glow2","bone":"Glow2","color":"ffffff00","attachment":"Glow2"},{"name":"34","bone":"JinBi","color":"ffffff00","attachment":"34"},{"name":"35","bone":"QianDai","color":"ffffff00","attachment":"35"},{"name":"37","bone":"Up","color":"ffffff00","attachment":"37"}],"skins":[{"name":"default","attachments":{"33":{"33":{"type":"mesh","uvs":[1,1,0,1,0,0,1,0],"triangles":[1,2,3,1,3,0],"vertices":[54,-54,-54,-54,-54,54,54,54],"hull":4,"edges":[0,2,2,4,4,6,0,6],"width":108,"height":108}},"34":{"34":{"type":"mesh","uvs":[1,1,0,1,0,0,1,0],"triangles":[1,2,3,1,3,0],"vertices":[39,-58,-39,-58,-39,58,39,58],"hull":4,"edges":[0,2,2,4,4,6,0,6],"width":78,"height":116}},"35":{"35":{"type":"mesh","uvs":[1,1,0,1,0,0,1,0],"triangles":[1,2,3,1,3,0],"vertices":[39,-58,-39,-58,-39,58,39,58],"hull":4,"edges":[0,2,2,4,4,6,0,6],"width":78,"height":116}},"37":{"37":{"type":"mesh","uvs":[1,1,0,1,0,0,1,0],"triangles":[1,2,3,1,3,0],"vertices":[53,-28,-53,-28,-53,29,53,29],"hull":4,"edges":[0,2,2,4,4,6,0,6],"width":106,"height":57}},"Glow":{"Glow":{"type":"mesh","color":"ffe800ff","uvs":[1,1,0,1,0,0,1,0],"triangles":[1,2,3,1,3,0],"vertices":[64,-64,-64,-64,-64,64,64,64],"hull":4,"edges":[0,2,2,4,4,6,0,6],"width":128,"height":128}},"Glow2":{"Glow2":{"type":"mesh","uvs":[1,1,0,1,0,0,1,0],"triangles":[1,2,3,1,3,0],"vertices":[167.44,-167.44,-167.44,-167.44,-167.44,167.44,167.44,167.44],"hull":4,"edges":[0,2,2,4,4,6,0,6],"width":256,"height":256}}}}],"animations":{"Ui_Double":{"slots":{"33":{"color":[{"color":"ffffffff"}]},"35":{"color":[{"color":"ffffffff"}]}},"bones":{"Di":{"rotate":[{},{"time":0.3333,"angle":-90},{"time":0.6667,"angle":180},{"time":1,"angle":90},{"time":1.3333}]}}},"Ui_PickUp":{"slots":{"33":{"color":[{"color":"ffffffff"}]},"34":{"color":[{"color":"ffffffff"}]}},"bones":{"Di":{"rotate":[{},{"time":0.3333,"angle":-90},{"time":0.6667,"angle":180},{"time":1,"angle":90},{"time":1.3333}]}}},"Ui_Up":{"slots":{"37":{"color":[{"color":"ffffff00"},{"time":0.1,"color":"ffffffff","curve":"stepped"},{"time":0.2667,"color":"ffffffff"},{"time":0.3333,"color":"ffffff00","curve":"stepped"},{"time":0.6667,"color":"ffffff00"}]},"Glow":{"color":[{"color":"ffffff00"},{"time":0.0667,"color":"ffffffff"},{"time":0.1667,"color":"ffffff00"}]},"Glow2":{"color":[{"color":"ffffff00"},{"time":0.0667,"color":"ffffffff"},{"time":0.1667,"color":"ffffff00"}]}},"bones":{"Up":{"scale":[{},{"time":0.1667,"x":1.692,"y":1.692},{"time":0.3333,"x":1.084,"y":1.084}]},"Glow1":{"scale":[{},{"time":0.1667,"x":2.205,"y":2.205}]},"Glow2":{"scale":[{},{"time":0.1667,"x":2.062,"y":2.062}]}}}}}